annotation.py
design/Capture.JPG
design/__init__.py
design/annotation.ui
gui/Delete.png
gui/__init__.py
packages/__init__.py
packages/convert_json_to_txt.py
packages/convert_to_json.py
packages/next_content.py
packages/refresh_clean.py
packages/save_in_json_format.py
packages/style_sheet.py
packages/table_view.py
spacy_annotation_tool-1.5.0.dist-info/LICENSE
spacy_annotation_tool-1.5.0.dist-info/METADATA
spacy_annotation_tool-1.5.0.dist-info/WHEEL
spacy_annotation_tool-1.5.0.dist-info/entry_points.txt
spacy_annotation_tool-1.5.0.dist-info/top_level.txt
spacy_annotation_tool-1.5.0.dist-info/RECORD
