Metadata-Version: 2.1
Name: spacy-annotation-tool
Version: 1.5.0
Summary: spacy annotation tool which help datascientist to label NER
Author-email: Yousafxai <ayazpk6630@gmail.com>
Classifier: Programming Language :: Python :: 3
Classifier: License :: OSI Approved :: MIT License
Classifier: Operating System :: OS Independent
License-File: LICENSE
Requires-Dist: pyqt5
Requires-Dist: pandas
